drf_writable_nested/__init__.py
drf_writable_nested/mixins.py
drf_writable_nested/serializers.py
drf_writable_nested-0.6.1.dist-info/LICENSE.md
drf_writable_nested-0.6.1.dist-info/METADATA
drf_writable_nested-0.6.1.dist-info/WHEEL
drf_writable_nested-0.6.1.dist-info/top_level.txt
drf_writable_nested-0.6.1.dist-info/RECORD
