Metadata-Version: 2.1
Name: drf-writable-nested
Version: 0.6.1
Summary: Writable nested helpers for django-rest-framework's serializers
Home-page: http://github.com/beda-software/drf-writable-nested
Author: beda.software
Author-email: drfwritablenested@beda.software
License: BSD
Keywords: drf restframework rest_framework django_rest_framework serializers drf_writable_nested
Platform: UNKNOWN
Classifier: Development Status :: 4 - Beta
Classifier: Environment :: Web Environment
Classifier: Framework :: Django
Classifier: Framework :: Django :: 2.2
Classifier: Framework :: Django :: 3.0
Classifier: Intended Audience :: Developers
Classifier: License :: OSI Approved :: BSD License
Classifier: Operating System :: OS Independent
Classifier: Programming Language :: Python
Classifier: Programming Language :: Python :: 3
Classifier: Programming Language :: Python :: 3 :: Only
Classifier: Programming Language :: Python :: 3.5
Classifier: Programming Language :: Python :: 3.6
Classifier: Programming Language :: Python :: 3.7
Classifier: Programming Language :: Python :: 3.8
Classifier: Topic :: Internet :: WWW/HTTP
Requires-Python: >=3.5
